{
    "defaults": {
        "directory": "bi-folder",
        "file": "bi-file-earmark"
    },
    "extensions": {
        "md": "bi-filetype-markdown",
        "txt": "bi-file-earmark-text",
        "pdf": "bi-file-earmark-pdf",
        "php": "bi-filetype-php",
        "js": "bi-filetype-js",
        "ts": "bi-filetype-typescript",
        "tsx": "bi-filetype-typescript",
        "css": "bi-filetype-css",
        "scss": "bi-filetype-scss",
        "less": "bi-filetype-less",
        "html": "bi-filetype-html",
        "htm": "bi-filetype-html",
        "json": "bi-filetype-json",
        "xml": "bi-filetype-xml",
        "yml": "bi-filetype-yaml",
        "yaml": "bi-filetype-yaml",
        "sh": "bi-terminal",
        "bash": "bi-terminal",
        "py": "bi-filetype-py",
        "rb": "bi-filetype-rb",
        "go": "bi-filetype-go",
        "rs": "bi-filetype-rust",
        "java": "bi-filetype-java",
        "c": "bi-filetype-c",
        "cpp": "bi-filetype-cpp",
        "h": "bi-filetype-h",
        "hpp": "bi-filetype-hpp",
        "sql": "bi-database",
        "png": "bi-file-earmark-image",
        "jpg": "bi-file-earmark-image",
        "jpeg": "bi-file-earmark-image",
        "gif": "bi-file-earmark-image",
        "svg": "bi-file-earmark-code",
        "ico": "bi-file-earmark-image",
        "webp": "bi-file-earmark-image",
        "zip": "bi-file-earmark-zip",
        "tar": "bi-file-earmark-zip",
        "gz": "bi-file-earmark-zip",
        "rar": "bi-file-earmark-zip",
        "7z": "bi-file-earmark-zip",
        "env": "bi-file-earmark-lock",
        "log": "bi-file-text",
        "csv": "bi-file-spreadsheet",
        "xls": "bi-file-spreadsheet",
        "xlsx": "bi-file-spreadsheet",
        "doc": "bi-file-earmark-word",
        "docx": "bi-file-earmark-word",
        "ppt": "bi-file-earmark-ppt",
        "pptx": "bi-file-earmark-ppt",
        "exe": "bi-file-earmark-binary",
        "dll": "bi-file-earmark-binary",
        "iso": "bi-disc",
        "mp3": "bi-file-earmark-music",
        "wav": "bi-file-earmark-music",
        "mp4": "bi-file-earmark-play",
        "avi": "bi-file-earmark-play",
        "mov": "bi-file-earmark-play",
        "mkv": "bi-file-earmark-play"
    },
    "custom": {},
    "paths": {}
}
